implicit/__init__.py
implicit/_nearest_neighbours.cp310-win_amd64.pyd
implicit/als.py
implicit/approximate_als.py
implicit/bpr.py
implicit/evaluation.cp310-win_amd64.pyd
implicit/lmf.py
implicit/nearest_neighbours.py
implicit/recommender_base.py
implicit/utils.py
implicit/ann/__init__.py
implicit/ann/annoy.py
implicit/ann/faiss.py
implicit/ann/nmslib.py
implicit/cpu/__init__.py
implicit/cpu/_als.cp310-win_amd64.pyd
implicit/cpu/als.py
implicit/cpu/bpr.cp310-win_amd64.pyd
implicit/cpu/lmf.cp310-win_amd64.pyd
implicit/cpu/matrix_factorization_base.py
implicit/cpu/topk.cp310-win_amd64.pyd
implicit/datasets/__init__.py
implicit/datasets/_download.py
implicit/datasets/lastfm.py
implicit/datasets/million_song_dataset.py
implicit/datasets/movielens.py
implicit/datasets/reddit.py
implicit/datasets/sketchfab.py
implicit/gpu/__init__.py
implicit/gpu/als.py
implicit/gpu/bpr.py
implicit/gpu/matrix_factorization_base.py
implicit-0.7.2.dist-info/LICENSE
implicit-0.7.2.dist-info/METADATA
implicit-0.7.2.dist-info/WHEEL
implicit-0.7.2.dist-info/top_level.txt
implicit-0.7.2.dist-info/RECORD
