Metadata-Version: 2.1
Name: implicit
Version: 0.7.2
Summary: Collaborative Filtering for Implicit Feedback Datasets
Home-page: http://github.com/benfred/implicit/
Author: Ben Frederickson
Author-email: ben@benfrederickson.com
License: MIT
Keywords: Matrix Factorization,Implicit Alternating Least Squares,Collaborative Filtering,Recommender Systems
Classifier: Development Status :: 4 - Beta
Classifier: Natural Language :: English
Classifier: Intended Audience :: Science/Research
Classifier: License :: OSI Approved :: MIT License
Classifier: Programming Language :: Python
Classifier: Programming Language :: Python :: 3
Classifier: Programming Language :: Cython
Classifier: Operating System :: OS Independent
Classifier: Topic :: Software Development :: Libraries :: Python Modules
License-File: LICENSE
Requires-Dist: numpy>=1.17.0
Requires-Dist: scipy>=0.16
Requires-Dist: tqdm>=4.27
Requires-Dist: threadpoolctl
